gridapi/__init__.py
gridapi/auth.py
gridapi/cli.py
gridapi/client.py
gridapi/exceptions.py
gridapi/py.typed
gridapi/managers/__init__.py
gridapi/managers/base.py
gridapi/managers/grid_manager.py
gridapi/managers/image_manager.py
gridapi/managers/taskflow_manager.py
gridapi/models/__init__.py
gridapi/models/base.py
gridapi/models/grid.py
gridapi/models/image.py
gridapi/query/__init__.py
gridapi/query/builder.py
gridapi/query/filters.py
gridapi/utils/__init__.py
gridapi/utils/helpers.py
gridapi/utils/validators.py
lnpi_gridapi-1.0.7.2.dist-info/licenses/LICENSE
lnpi_gridapi-1.0.7.2.dist-info/METADATA
lnpi_gridapi-1.0.7.2.dist-info/WHEEL
lnpi_gridapi-1.0.7.2.dist-info/entry_points.txt
lnpi_gridapi-1.0.7.2.dist-info/top_level.txt
lnpi_gridapi-1.0.7.2.dist-info/RECORD
