Metadata-Version: 2.4
Name: lnpi_gridapi
Version: 1.0.7.2
Summary: Python client library for LNPI Grid API
Author-email: "Kelvin O. Lim" <lim.kelvino@gmail.com>
Maintainer-email: "Kelvin O. Lim" <lim.kelvino@gmail.com>
License-Expression: MIT
Project-URL: Homepage, https://github.com/kelvinlim/grid_api
Keywords: grid,api,client,medical,research,imaging,clinical-trials
Classifier: Development Status :: 4 - Beta
Classifier: Intended Audience :: Developers
Classifier: Intended Audience :: Science/Research
Classifier: Intended Audience :: Healthcare Industry
Classifier: Operating System :: OS Independent
Classifier: Programming Language :: Python :: 3
Classifier: Programming Language :: Python :: 3.8
Classifier: Programming Language :: Python :: 3.9
Classifier: Programming Language :: Python :: 3.10
Classifier: Programming Language :: Python :: 3.11
Classifier: Programming Language :: Python :: 3.12
Classifier: Topic :: Software Development :: Libraries :: Python Modules
Classifier: Topic :: Scientific/Engineering :: Medical Science Apps.
Classifier: Topic :: Scientific/Engineering :: Information Analysis
Classifier: Topic :: Internet :: WWW/HTTP :: Dynamic Content
Classifier: Topic :: System :: Networking
Requires-Python: >=3.8
License-File: LICENSE
Requires-Dist: requests>=2.28.0
Requires-Dist: pydantic>=1.10.0
Requires-Dist: python-dateutil>=2.8.0
Requires-Dist: typing-extensions>=4.0.0
Provides-Extra: async
Requires-Dist: aiohttp>=3.8.0; extra == "async"
Provides-Extra: cli
Requires-Dist: click>=8.0.0; extra == "cli"
Requires-Dist: rich>=12.0.0; extra == "cli"
Provides-Extra: dev
Requires-Dist: pytest>=7.0.0; extra == "dev"
Requires-Dist: pytest-asyncio>=0.21.0; extra == "dev"
Requires-Dist: black>=22.0.0; extra == "dev"
Requires-Dist: isort>=5.10.0; extra == "dev"
Requires-Dist: mypy>=1.0.0; extra == "dev"
Requires-Dist: flake8>=5.0.0; extra == "dev"
Requires-Dist: pyinstaller>=5.0.0; extra == "dev"
Provides-Extra: docs
Requires-Dist: sphinx>=5.0.0; extra == "docs"
Requires-Dist: sphinx-rtd-theme>=1.0.0; extra == "docs"
Requires-Dist: myst-parser>=0.18.0; extra == "docs"
Provides-Extra: all
Requires-Dist: aiohttp>=3.8.0; extra == "all"
Requires-Dist: click>=8.0.0; extra == "all"
Requires-Dist: rich>=12.0.0; extra == "all"
Requires-Dist: pytest>=7.0.0; extra == "all"
Requires-Dist: pytest-asyncio>=0.21.0; extra == "all"
Requires-Dist: black>=22.0.0; extra == "all"
Requires-Dist: isort>=5.10.0; extra == "all"
Requires-Dist: mypy>=1.0.0; extra == "all"
Requires-Dist: flake8>=5.0.0; extra == "all"
Requires-Dist: pyinstaller>=5.0.0; extra == "all"
Requires-Dist: sphinx>=5.0.0; extra == "all"
Requires-Dist: sphinx-rtd-theme>=1.0.0; extra == "all"
Requires-Dist: myst-parser>=0.18.0; extra == "all"
Dynamic: license-file
